django_postgres_delete_cascade-2.0a1.dist-info/pbr.json
django_postgres_delete_cascade-2.0a1.dist-info/WHEEL
django_postgres_delete_cascade-2.0a1.dist-info/metadata.json
django_postgres_delete_cascade-2.0a1.dist-info/DESCRIPTION.rst
django_postgres_delete_cascade-2.0a1.dist-info/METADATA
django_postgres_delete_cascade-2.0a1.dist-info/top_level.txt
django_postgres_delete_cascade-2.0a1.dist-info/RECORD
django_postgres_delete_cascade/base.py
django_postgres_delete_cascade/__init__.py
django_postgres_delete_cascade/schema.py
