Metadata-Version: 2.0
Name: django-postgres-delete-cascade
Version: 2.0a1
Summary: PostgreSQL engine for Django that supports "ON DELETE CASCADE" at the database level
Home-page: https://github.com/2degrees/django-postgres-delete-cascade
Author: 2degrees Limited
Author-email: 2degrees-floss@googlegroups.com
License: BSD (http://dev.2degreesnetwork.com/p/2degrees-license.html)
Keywords: django postgres cascade cascading delete foreign key keys
Platform: UNKNOWN
Classifier: Development Status :: 5 - Production/Stable
Classifier: Framework :: Django
Classifier: Intended Audience :: Developers
Classifier: License :: OSI Approved :: BSD License
Classifier: Topic :: Database
Requires-Dist: Django (>=1.8)
Requires-Dist: psycopg2 (>=2.5)
